tnum/__init__.py
tnum/tibetan_numbers.py
tnum-0.2.0.dist-info/licenses/LICENSE
tnum-0.2.0.dist-info/METADATA
tnum-0.2.0.dist-info/WHEEL
tnum-0.2.0.dist-info/top_level.txt
tnum-0.2.0.dist-info/RECORD
