Metadata-Version: 2.4
Name: tnum
Version: 0.2.0
Summary: A Python library for converting between English, Tibetan, and Roman numerals
Author: tnum contributors
License: MIT
Project-URL: Homepage, https://github.com/tenznz/tnum
Project-URL: Bug Reports, https://github.com/tenznz/tnum/issues
Project-URL: Source, https://github.com/tenznz/tnum
Keywords: tibetan,roman,numerals,numbers,unicode,conversion
Classifier: Development Status :: 3 - Alpha
Classifier: Intended Audience :: Developers
Classifier: License :: OSI Approved :: MIT License
Classifier: Programming Language :: Python :: 3
Classifier: Programming Language :: Python :: 3.7
Classifier: Programming Language :: Python :: 3.8
Classifier: Programming Language :: Python :: 3.9
Classifier: Programming Language :: Python :: 3.10
Classifier: Programming Language :: Python :: 3.11
Classifier: Topic :: Software Development :: Libraries :: Python Modules
Classifier: Topic :: Text Processing :: Linguistic
Requires-Python: >=3.7
License-File: LICENSE
Provides-Extra: dev
Requires-Dist: pytest>=7.0.0; extra == "dev"
Requires-Dist: pytest-cov>=4.0.0; extra == "dev"
Dynamic: license-file
